LICENSE
MANIFEST.in
README.md
requirements.txt
setup.cfg
setup.py
handyman/__init__.py
handyman/__main__.py
handyman/grpc_utils.py
handyman/helpers.py
handyman/io.py
handyman/json_utils.py
handyman/log.py
handyman/prometheus.py
handyman/sentry.py
handyman.egg-info/PKG-INFO
handyman.egg-info/SOURCES.txt
handyman.egg-info/dependency_links.txt
handyman.egg-info/namespace_packages.txt
handyman.egg-info/not-zip-safe
handyman.egg-info/requires.txt
handyman.egg-info/top_level.txt
handyman/cli/__init__.py
handyman/cli/proto_gen.py
handyman/crypto/__init__.py
handyman/crypto/cache.py
handyman/crypto/crypto.py
handyman/crypto/environment_variables.py
handyman/crypto/exceptions.py
handyman/crypto/vault.py
handyman/events/__init__.py
handyman/events/event_types.py
handyman/events/exceptions.py
handyman/events/goroutine.py
handyman/events/sqs.py
handyman/exceptions/__init__.py